xaal/__init__.py
xaal/zwavejs/__init__.py
xaal/zwavejs/__main__.py
xaal/zwavejs/const.py
xaal/zwavejs/devices.py
xaal/zwavejs/gw.py
xaal_zwavejs-0.2.1.dist-info/METADATA
xaal_zwavejs-0.2.1.dist-info/WHEEL
xaal_zwavejs-0.2.1.dist-info/top_level.txt
xaal_zwavejs-0.2.1.dist-info/RECORD
